numanalysis/__init__.py
numanalysis/cholesky.py
numanalysis/lu.py
numanalysis-0.1.1.dist-info/METADATA
numanalysis-0.1.1.dist-info/WHEEL
numanalysis-0.1.1.dist-info/top_level.txt
numanalysis-0.1.1.dist-info/RECORD
