Metadata-Version: 2.4
Name: numanalysis
Version: 0.1.1
Summary: Package for LU decomp
Home-page: https://github.com/1030minouche
Author: Aminouche
Author-email: solenouche@aminouche.fr
Classifier: Programming Language :: Python :: 2
Classifier: License :: OSI Approved :: MIT License
Classifier: Operating System :: OS Independent
Requires-Python: >=2.7
Dynamic: author
Dynamic: author-email
Dynamic: classifier
Dynamic: description
Dynamic: description-content-type
Dynamic: home-page
Dynamic: requires-python
Dynamic: summary
